pistl/__init__.py
pistl/converter.py
pistl/core.py
pistl/pist_exceptions.py
pistl/shapes.py
pistl/utilities.py
pistl-1.2.0.dist-info/LICENSE
pistl-1.2.0.dist-info/WHEEL
pistl-1.2.0.dist-info/METADATA
pistl-1.2.0.dist-info/RECORD
