Metadata-Version: 2.1
Name: pistl
Version: 1.2.0
Summary: Python library to generate STL format files for common shapes and geometries.
Home-page: https://github.com/sumanan047/pistl
License: MIT
Keywords: stl,3-D Shapes
Author: Suman Saurabh
Author-email: sumanan047@gmail.com
Maintainer: Suman Saurabh
Maintainer-email: sumanan047@gmail.com
Requires-Python: >=3.10,<4.0
Classifier: License :: OSI Approved :: MIT License
Classifier: Programming Language :: Python :: 3
Classifier: Programming Language :: Python :: 3.10
Requires-Dist: ipykernel (==6.27.1)
Requires-Dist: numpy (==1.26.2)
Requires-Dist: pip (==24.0.0)
Requires-Dist: pyvista[jupyter] (>=0.38.1)
Requires-Dist: trame (==3.3.0)
Requires-Dist: trame-components (==2.2.1)
Requires-Dist: trame-vuetify (==2.3.1)
Requires-Dist: vtk (==9.3.0)
Project-URL: Repository, https://github.com/sumanan047/pistl
